mcore/__init__.py
mcore/type/__init__.py
mcore/type/generic.py
mCore-0.2.2.dist-info/LICENSE.txt
mCore-0.2.2.dist-info/METADATA
mCore-0.2.2.dist-info/WHEEL
mCore-0.2.2.dist-info/top_level.txt
mCore-0.2.2.dist-info/RECORD
