Metadata-Version: 2.1
Name: mCore
Version: 0.2.2
Summary: Package Core personnel memnoch
Home-page: https://github.com/pyscaffold/pyscaffold/
Author: memnoch9178
Author-email: guillaume@ldmail.fr
License: MIT
Project-URL: Documentation, https://pyscaffold.org/
Platform: any
Classifier: Development Status :: 4 - Beta
Classifier: Programming Language :: Python
License-File: LICENSE.txt
Requires-Dist: importlib-metadata; python_version < "3.8"
Provides-Extra: testing
Requires-Dist: setuptools; extra == "testing"
Requires-Dist: pytest; extra == "testing"
Requires-Dist: pytest-cov; extra == "testing"
